MANIFEST.in
README.md
requirements.txt
setup.py
calibrating/__info__.py
calibrating/__init__.py
calibrating/boards.py
calibrating/camera.py
calibrating/epipolar_geometry.py
calibrating/feature_libs.py
calibrating/flow_utils.py
calibrating/multi_boards.py
calibrating/reconstruction_epipolar_geometry.py
calibrating/reconstruction_with_board.py
calibrating/stereo_camera.py
calibrating/stereo_matching.py
calibrating/utils.py
calibrating.egg-info/PKG-INFO
calibrating.egg-info/SOURCES.txt
calibrating.egg-info/dependency_links.txt
calibrating.egg-info/requires.txt
calibrating.egg-info/top_level.txt